<annotation><filename>1864.jpg</filename><folder>example_folder</folder><source><sourceImage>The MIT-CSAIL database of objects and scenes</sourceImage><sourceAnnotation>LabelMe Webtool</sourceAnnotation></source><object><name>skip</name><deleted>0</deleted><verified>0</verified><occluded>no</occluded><attributes>skip</attributes><parts><hasparts></hasparts><ispartof></ispartof></parts><date>19-Dec-2017 07:48:43</date><id>0</id><type>bounding_box</type><polygon><username>hussen_1</username><pt><x>3305</x><y>1950</y></pt><pt><x>3947</x><y>1950</y></pt><pt><x>3947</x><y>3776</y></pt><pt><x>3305</x><y>3776</y></pt></polygon></object><imagesize><nrows></nrows><ncols></ncols></imagesize></annotation>